[{"mmsi":"244002007","vessel":"BRISANI","imo":"0","callsign":"PH3644","destination":"AMSTERDAM","lastReport":"24-02-2019 23:32 UTC","currentLocation":"2459 2534 2256"},{"mmsi":"244002106","vessel":"LINA","imo":"0","callsign":"PF4208","destination":"","lastReport":"24-02-2019 23:32 UTC","currentLocation":"2623"},{"mmsi":"244002136","vessel":"BALDER","imo":"0","callsign":"PF4425","destination":"HARLINGEN","lastReport":"24-02-2019 23:32 UTC","currentLocation":"2112"},{"mmsi":"244002152","vessel":"DISPONIBEL","imo":"0","callsign":"PG9879","destination":"","lastReport":"24-02-2019 23:29 UTC","currentLocation":"2734"},{"mmsi":"244002228","vessel":"COLORADO","imo":"0","callsign":"PH5353","destination":"MOERDIJK","lastReport":"24-02-2019 23:33 UTC","currentLocation":"2077 2241 2835 2642 2392"},{"mmsi":"244002247","vessel":"DORUS","imo":"0","callsign":"PF7936","destination":"AMSTERDAM","lastReport":"24-02-2019 23:33 UTC","currentLocation":"2256 2534 2278 2459 2515"},{"mmsi":"244003000","vessel":"LADY CHRISTINA","imo":"9201815","callsign":"PFAC","destination":"DEEME","lastReport":"24-02-2019 23:33 UTC","currentLocation":"2262"},{"mmsi":"244005773","vessel":"ROBBE","imo":"0","callsign":"PF7845","destination":"","lastReport":"24-02-2019 23:30 UTC","currentLocation":"2241"},{"mmsi":"244005823","vessel":"REVOLUTION","imo":"0","callsign":"PG9991","destination":"","lastReport":"24-02-2019 23:32 UTC","currentLocation":"2399"},{"mmsi":"244005869","vessel":"STT EXCEPTIONAL","imo":"0","callsign":"PF9015","destination":"NL AMS","lastReport":"24-02-2019 23:30 UTC","currentLocation":"2459 2515"},{"mmsi":"244005917","vessel":"PIZ AMALIA","imo":"0","callsign":"HE7207","destination":"LADENBURG","lastReport":"24-02-2019 23:32 UTC","currentLocation":"2241 2623"},{"mmsi":"244005982","vessel":"LUCKY STRIPPER","imo":"0","callsign":"PG3311","destination":"","lastReport":"24-02-2019 23:32 UTC","currentLocation":"2515 2278"},{"mmsi":"244006037","vessel":"MARTENS 5","imo":"0","callsign":"PG3235","destination":"ROTTERDAM","lastReport":"24-02-2019 23:33 UTC","currentLocation":"2241 2588 2347 2392 2548 2475 2642 2077"},{"mmsi":"244006435","vessel":"JAN 7","imo":"0","callsign":"PA2053","destination":"","lastReport":"24-02-2019 23:30 UTC","currentLocation":"2515"},{"mmsi":"244007000","vessel":"TWISTER","imo":"0","callsign":"PCAB","destination":"AMSTERDAM","lastReport":"24-02-2019 23:33 UTC","currentLocation":"2256 2459 2346 2534 2278 2515"},{"mmsi":"244010000","vessel":"VARNEBANK","imo":"0","callsign":"PIEJ","destination":"","lastReport":"24-02-2019 23:31 UTC","currentLocation":"2510 2097"},{"mmsi":"244010004","vessel":"LACOMBLE","imo":"0","callsign":"PG4613","destination":"DEN HELDER","lastReport":"24-02-2019 23:32 UTC","currentLocation":"2065 2593"},{"mmsi":"244010030","vessel":"DESPERADO","imo":"0","callsign":"PG4862","destination":"ARA","lastReport":"24-02-2019 23:33 UTC","currentLocation":"2347 2642 2815 2629 2548 2077"},{"mmsi":"244010031","vessel":"VITESSE","imo":"0","callsign":"PH3269","destination":"BASEL-ROTTERDAM","lastReport":"24-02-2019 23:32 UTC","currentLocation":"2241"},{"mmsi":"244010042","vessel":"TURQUOISE","imo":"0","callsign":"PD5109","destination":"B","lastReport":"24-02-2019 23:32 UTC","currentLocation":"2241 2588 2347 2077 2392 2642 2185"},{"mmsi":"244010069","vessel":"ZANDLOPER","imo":"0","callsign":"PD0","destination":"ONDERWEG","lastReport":"24-02-2019 23:33 UTC","currentLocation":"2241 2379 2163 2734"},{"mmsi":"244010082","vessel":"AMBITIE","imo":"0","callsign":"PD6418","destination":"AUSTRALIEHAVEN","lastReport":"24-02-2019 23:32 UTC","currentLocation":"2236"},{"mmsi":"244010114","vessel":"LAUS DEO","imo":"0","callsign":"PD2776","destination":"","lastReport":"24-02-2019 23:32 UTC","currentLocation":"2590"},{"mmsi":"244010131","vessel":"AMOUREUS","imo":"0","callsign":"PD3483","destination":"ZENNEWIJNEN","lastReport":"24-02-2019 23:32 UTC","currentLocation":"2435 2256 2534 2236 2515 2459 2346 2278"},{"mmsi":"244010160","vessel":"JULIA","imo":"0","callsign":"PD5281","destination":"","lastReport":"24-02-2019 23:05 UTC","currentLocation":""},{"mmsi":"244010172","vessel":"ZORG EN VLIJT","imo":"0","callsign":"PI3851","destination":"IJSSELMEER","lastReport":"24-02-2019 23:33 UTC","currentLocation":"2671 2112 2268 2065"},{"mmsi":"244010182","vessel":"KAAT MOSSEL","imo":"0","callsign":"PC2219","destination":"","lastReport":"24-02-2019 23:20 UTC","currentLocation":""},{"mmsi":"244010183","vessel":"FREYR","imo":"0","callsign":"PF2215","destination":"WADDINXVEEN","lastReport":"24-02-2019 23:27 UTC","currentLocation":"2077 2588 2381 2241"},{"mmsi":"244010190","vessel":"REINOD 1","imo":"0","callsign":"PD5777","destination":"R.DAM","lastReport":"24-02-2019 23:33 UTC","currentLocation":"2588 2642 2140 2916 2677 2096 2077"},{"mmsi":"244010219","vessel":"REINOD 6","imo":"0","callsign":"PF5299","destination":"R.DAM HAVENS","lastReport":"24-02-2019 23:33 UTC","currentLocation":"2077"},{"mmsi":"244010253","vessel":"VEERHAVEN VII","imo":"0","callsign":"PI3032","destination":"SCHWELGERN","lastReport":"24-02-2019 23:18 UTC","currentLocation":""},{"mmsi":"244010258","vessel":"DOLFIJN","imo":"0","callsign":"PD8767","destination":"","lastReport":"24-02-2019 23:32 UTC","currentLocation":"2065 2697 2268"},{"mmsi":"244010269","vessel":"CHALLENGER","imo":"0","callsign":"PD9339","destination":"MAASTRICHT","lastReport":"24-02-2019 23:33 UTC","currentLocation":"2559"},{"mmsi":"244010283","vessel":"RAAF","imo":"0","callsign":"PI5517","destination":"KAAG","lastReport":"24-02-2019 23:30 UTC","currentLocation":"2224 2497 2086 2435"},{"mmsi":"244010311","vessel":"MAGNIFIQUE II","imo":"0","callsign":"PH8702","destination":"AMSTERDAM","lastReport":"24-02-2019 23:12 UTC","currentLocation":""},{"mmsi":"244010328","vessel":"ANNA VAN ORANJE","imo":"0","callsign":"PC3305","destination":"BESTEMMING","lastReport":"24-02-2019 23:19 UTC","currentLocation":""},{"mmsi":"244010334","vessel":"LINQUENDA","imo":"0","callsign":"PF6991","destination":"ERGENS BENJE NERGENP","lastReport":"24-02-2019 23:32 UTC","currentLocation":"2350"},{"mmsi":"244010349","vessel":"RIVER QUEEN","imo":"0","callsign":"PC5495","destination":"","lastReport":"24-02-2019 23:32 UTC","currentLocation":"2126"},{"mmsi":"244010352","vessel":"MARTENS 10","imo":"0","callsign":"PF7390","destination":"ROTTERDAM","lastReport":"24-02-2019 23:32 UTC","currentLocation":"2292 2515"},{"mmsi":"244010358","vessel":"GEERTJE H","imo":"0","callsign":"PD2253","destination":"","lastReport":"24-02-2019 23:20 UTC","currentLocation":""},{"mmsi":"244010374","vessel":"IRON LADY","imo":"0","callsign":"PC 3040","destination":"","lastReport":"24-02-2019 23:30 UTC","currentLocation":"2534"},{"mmsi":"244010377","vessel":"TWIXX","imo":"0","callsign":"PF7812","destination":"","lastReport":"24-02-2019 23:30 UTC","currentLocation":"2134 2071"},{"mmsi":"244010398","vessel":"DRIE GEZUSTERS","imo":"0","callsign":"PC7537","destination":"AMSTERDAM","lastReport":"24-02-2019 23:30 UTC","currentLocation":"2515 2278 2256 2346 2459"},{"mmsi":"244010437","vessel":"NIJVERHEID","imo":"0","callsign":"PD9605","destination":"","lastReport":"24-02-2019 23:33 UTC","currentLocation":"2096 2548 2077"},{"mmsi":"244010489","vessel":"RAPITARD","imo":"0","callsign":"PH3774","destination":"LEVERKUSEN","lastReport":"24-02-2019 23:33 UTC","currentLocation":"2097 2086 2555 2347 2241 2276 2435 2468"},{"mmsi":"244010511","vessel":"SOMBRA","imo":"0","callsign":"PI3490","destination":"ROTTERDAM CALANDKAN","lastReport":"24-02-2019 23:33 UTC","currentLocation":"2961 2241 2347 2276 2555 2549 2097 2468 2077"},{"mmsi":"244010542","vessel":"VENTO","imo":"0","callsign":"PD7685","destination":"AMSTERDAM ARENA","lastReport":"24-02-2019 23:33 UTC","currentLocation":"2112"},{"mmsi":"244010568","vessel":"HEBO-CAT 11","imo":"0","callsign":"PF3948","destination":"","lastReport":"24-02-2019 23:33 UTC","currentLocation":"2403 2464 2126 2603 2413 2577"},{"mmsi":"244010573","vessel":"PIA","imo":"0","callsign":"PD7004","destination":"DEN HAAG","lastReport":"24-02-2019 23:31 UTC","currentLocation":"2677 2916 2096 2077"},{"mmsi":"244010595","vessel":"T'AI - SHANG","imo":"0","callsign":"PD4443","destination":"GRIMBERGEN","lastReport":"24-02-2019 23:33 UTC","currentLocation":"2392 2241 2642"}]